kubehelm/__init__.py
kubehelm/apps.py
kubehelm/context.py
kubehelm/execute.py
kubehelm/manager.py
kubehelm/objects.py
kubehelm/script.py
kubehelm/settings.py
kubehelm/template.py
kubehelm/models/__init__.py
kubehelm/models/base.py
kubehelm/models/db.py
kubehelm/models/helm.py
kubehelm/models/manifest.py
kubehelm/scripts/cert_manager.bash
kubehelm/scripts/helm.bash
kubehelm/scripts/ingress.bash
kubehelm/scripts/letsencrypt_production.bash
kubehelm/scripts/letsencrypt_staging.bash
kubehelm/scripts/update_helm_repo.bash
kubehelm/templates/bitnami/mariadb.yaml
kubehelm/templates/bitnami/osclass.yaml
kubehelm/templates/bitnami/phpmyadmin.yaml
kubehelm/templates/bitnami/wordpress.yaml
kubehelm/templates/bitnami/wordpress2.yaml
kubehelm/templates/ingress/aws.yaml
kubehelm/templates/ingress/baremetal.yaml
kubehelm/templates/ingress/cloud.yaml
kubehelm/templates/ingress/do.yaml
kubehelm/templates/ingress/kind.yaml
kubehelm/templates/manifests/django.yaml
kubehelm/templates/manifests/whoami.yaml
kubehelm/templates/manifests/wordpress.yaml
kubehelm/templates/manifests/wp-bitnami.yaml
kubehelm/templates/manifests/wp.yaml
kubehelm/templates/manifests/network/ingress.yaml
kubehelm/templates/manifests/network/node-port.yaml
kubehelm/templates/manifests/network/service.yaml
kubehelm/templates/manifests/quota/cpu_200.yaml
kubehelm/templates/tests/test.yaml
kubehelm-0.3.0.dist-info/METADATA
kubehelm-0.3.0.dist-info/WHEEL
kubehelm-0.3.0.dist-info/entry_points.txt
kubehelm-0.3.0.dist-info/top_level.txt
kubehelm-0.3.0.dist-info/RECORD
