Metadata-Version: 2.1
Name: kubehelm
Version: 0.3.0
Summary: Asim small example package
Home-page: https://github.com/asim3/kubehelm
Author: Asim Altuwayjiri
License: MIT
Project-URL: Bug Tracker, https://github.com/asim3/kubehelm/issues
Project-URL: Source, https://github.com/asim3/kubehelm
Keywords: kubernetes,deploy,production,helm,ingress,network
Platform: UNKNOWN
Classifier: Development Status :: 3 - Alpha
Classifier: Topic :: Software Development :: Build Tools
Classifier: Intended Audience :: Developers
Classifier: Programming Language :: Python :: 3
Classifier: Operating System :: OS Independent
Classifier: License :: OSI Approved :: MIT License
Classifier: Programming Language :: Python :: 3
Classifier: Programming Language :: Python :: 3.6
Classifier: Programming Language :: Python :: 3.7
Classifier: Programming Language :: Python :: 3.8
Classifier: Programming Language :: Python :: 3.9
Classifier: Programming Language :: Python :: 3 :: Only
Requires-Python: >=3.6, <4
Requires-Dist: requests
Requires-Dist: kubernetes (==12.0.1)
Requires-Dist: Jinja2 (==2.11.3)
Requires-Dist: mysql-connector-python
